{"content":"Dzi\u015b | W ostatnim czasie **Soli Deo bardzo&nbsp;dynamicznie si\u0119&nbsp;rozwija.** Nasze zaproszenia przyjmuj\u0105 kolejne **wybitne i s\u0142awne osoby**, w spotkaniach bior\u0105 udzia\u0142 **tysi\u0105ce uczestnik\u00f3w**, informacje o organizowanych wydarzeniach pojawiaj\u0105 si\u0119 w **najwi\u0119kszych mediach**, wielk\u0105 popularno\u015bci\u0105 ciesz\u0105 si\u0119 filmy zamieszczane na Youtube. \n\nNowa sytuacja, w jakiej si\u0119 znale\u017ali\u015bmy, wymaga nowych rozwi\u0105za\u0144. Dlatego chcemy si\u0119 zwr\u00f3ci\u0107 do Was z pro\u015bb\u0105 o pomoc w dalszym rozwoju i przedstawi\u0107 Wam now\u0105 propozycj\u0119 wsparcia - **Klub Sympatyk\u00f3w Soli Deo**.\nZapraszamy do zapoznania si\u0119 z nasz\u0105 propozycj\u0105 i do wsparcia naszego dzia\u0142ania\n         ","source":"jos","title":"Klub Sympatyk\u00f3w Soli Deo","publish_down":"0000-00-00 00:00:00","created":"2010-01-20 12:49:45","id":"850","original_introtext":"Dzi\u015b | <div align=\"justify\">W ostatnim czasie <strong>Soli Deo bardzo&nbsp;dynamicznie si\u0119&nbsp;rozwija.<\/strong> Nasze zaproszenia przyjmuj\u0105 kolejne <strong>wybitne i s\u0142awne osoby<\/strong>, w spotkaniach bior\u0105 udzia\u0142 <strong>tysi\u0105ce uczestnik\u00f3w<\/strong>, informacje o organizowanych wydarzeniach pojawiaj\u0105 si\u0119 w <strong>najwi\u0119kszych mediach<\/strong>, wielk\u0105 popularno\u015bci\u0105 ciesz\u0105 si\u0119 filmy zamieszczane na Youtube. <br><p>Nowa sytuacja, w jakiej si\u0119 znale\u017ali\u015bmy, wymaga nowych rozwi\u0105za\u0144. Dlatego chcemy si\u0119 zwr\u00f3ci\u0107 do Was z pro\u015bb\u0105 o pomoc w dalszym rozwoju i przedstawi\u0107 Wam now\u0105 propozycj\u0119 wsparcia - <strong>Klub Sympatyk\u00f3w Soli Deo<\/strong>.<br><\/p><p>Zapraszamy do zapoznania si\u0119 z nasz\u0105 propozycj\u0105 i do wsparcia naszego dzia\u0142ania<\/p><\/div>         ","original_fulltext":"","text-date":"Dzi\u015b (data umieszczenia na nowej stronie: 2010-01-20 12:49:45)"}