{"content":"&lt;object id=\"vp1mL1IG\" width=\"648\" height=\"364\" classid=\"clsid:d27cdb6e-ae6d-11cf-96b8-444553540000\"&gt;&lt;param name=\"movie\" value=\"http:\/\/static.animoto.com\/swf\/w.swf?w=swf\/vp1&e=1352505765&f=mL1IGV05v2maxAb1yhMWyA&d=39&m=b&r=360p&volume=100&start_res=360p&i=m&options=autostart\"&gt;&lt;\/param&gt;&lt;param name=\"allowFullScreen\" value=\"true\"&gt;&lt;\/param&gt;&lt;param name=\"allowscriptaccess\" value=\"always\"&gt;&lt;\/param&gt;&lt;embed id=\"vp1mL1IG\" src=\"http:\/\/static.animoto.com\/swf\/w.swf?w=swf\/vp1&e=1352505765&f=mL1IGV05v2maxAb1yhMWyA&d=39&m=b&r=360p&volume=100&start_res=360p&i=m&options=autostart\" type=\"application\/x-shockwave-flash\" allowscriptaccess=&\nquot;always\" allowfullscreen=\"true\" width=\"648\" height=\"364\"&gt;&lt;\/embed&gt;&lt;\/object&gt;\n\n<!--CONTENT FROM OLD SERVER (jos before 2013): &lt;object id=\"vp1mL1IG\" width=\"648\" height=\"364\" classid=\"clsid:d27cdb6e-ae6d-11cf-96b8-444553540000\"&gt;&lt;param name=\"movie\" value=\"http:\/\/static.animoto.com\/swf\/w.swf?w=swf\/vp1&e=1352505765&f=mL1IGV05v2maxAb1yhMWyA&d=39&m=b&r=360p&volume=100&start_res=360p&i=m&options=autostart\"&gt;&lt;\/param&gt;&lt;param name=\"allowFullScreen\" value=\"true\"&gt;&lt;\/param&gt;&lt;param name=\"allowscriptaccess\" value=\"always\"&gt;&lt;\/param&gt;&lt;embed id=\"vp1mL1IG\" src=\"http:\/\/static.animoto.com\/swf\/w.swf?w=swf\/vp1&e=1352505765&f=mL1IGV05v2maxAb1yhMWyA&d=39&m=b&r=360p&volume=100&start_res=360p&i=m&options=autostart\" type=\"application\/x-shockwave-flash\" allowscriptaccess=\"always\" allowfullscreen=\"true\" width=\"648\" height=\"364\"&gt;&lt;\/embed&gt;&lt;\/object&gt;\n-->","source":"jos","title":"czekamy na CIEBIE!","publish_down":"0000-00-00 00:00:00","created":"2012-11-10 00:03:20","id":"1136","original_introtext":"&lt;object id=\"vp1mL1IG\" width=\"648\" height=\"364\" classid=\"clsid:d27cdb6e-ae6d-11cf-96b8-444553540000\"&gt;&lt;param name=\"movie\" value=\"http:\/\/static.animoto.com\/swf\/w.swf?w=swf\/vp1&amp;e=1352505765&amp;f=mL1IGV05v2maxAb1yhMWyA&amp;d=39&amp;m=b&amp;r=360p&amp;volume=100&amp;start_res=360p&amp;i=m&amp;options=autostart\"&gt;&lt;\/param&gt;&lt;param name=\"allowFullScreen\" value=\"true\"&gt;&lt;\/param&gt;&lt;param name=\"allowscriptaccess\" value=\"always\"&gt;&lt;\/param&gt;&lt;embed id=\"vp1mL1IG\" src=\"http:\/\/static.animoto.com\/swf\/w.swf?w=swf\/vp1&amp;e=1352505765&amp;f=mL1IGV05v2maxAb1yhMWyA&amp;d=39&amp;m=b&amp;r=360p&amp;volume=100&amp;start_res=360p&amp;i=m&amp;options=autostart\" type=\"application\/x-shockwave-flash\" allowscriptaccess=\"always\" allowfullscreen=\"true\" width=\"648\" height=\"364\"&gt;&lt;\/embed&gt;&lt;\/object&gt;","original_fulltext":"","after-2013-move":{"content":"&lt;object id=\"vp1mL1IG\" width=\"648\" height=\"364\" classid=\"clsid:d27cdb6e-ae6d-11cf-96b8-444553540000\"&gt;&lt;param name=\"movie\" value=\"http:\/\/static.animoto.com\/swf\/w.swf?w=swf\/vp1&e=1352505765&f=mL1IGV05v2maxAb1yhMWyA&d=39&m=b&r=360p&volume=100&start_res=360p&i=m&options=autostart\"&gt;&lt;\/param&gt;&lt;param name=\"allowFullScreen\" value=\"true\"&gt;&lt;\/param&gt;&lt;param name=\"allowscriptaccess\" value=\"always\"&gt;&lt;\/param&gt;&lt;embed id=\"vp1mL1IG\" src=\"http:\/\/static.animoto.com\/swf\/w.swf?w=swf\/vp1&e=1352505765&f=mL1IGV05v2maxAb1yhMWyA&d=39&m=b&r=360p&volume=100&start_res=360p&i=m&options=autostart\" type=\"application\/x-shockwave-flash\" allowscriptaccess=&\nquot;always\" allowfullscreen=\"true\" width=\"648\" height=\"364\"&gt;&lt;\/embed&gt;&lt;\/object&gt;","source":"jom","title":"czekamy na CIEBIE!","publish_down":"0000-00-00 00:00:00","created":"2013-05-08 20:59:32","id":"1136","original_introtext":"&lt;object id=\"vp1mL1IG\" width=\"648\" height=\"364\" classid=\"clsid:d27cdb6e-ae6d-11cf-96b8-444553540000\"&gt;&lt;param name=\"movie\" value=\"http:\/\/static.animoto.com\/swf\/w.swf?w=swf\/vp1&amp;e=1352505765&amp;f=mL1IGV05v2maxAb1yhMWyA&amp;d=39&amp;m=b&amp;r=360p&amp;volume=100&amp;start_res=360p&amp;i=m&amp;options=autostart\"&gt;&lt;\/param&gt;&lt;param name=\"allowFullScreen\" value=\"true\"&gt;&lt;\/param&gt;&lt;param name=\"allowscriptaccess\" value=\"always\"&gt;&lt;\/param&gt;&lt;embed id=\"vp1mL1IG\" src=\"http:\/\/static.animoto.com\/swf\/w.swf?w=swf\/vp1&amp;e=1352505765&amp;f=mL1IGV05v2maxAb1yhMWyA&amp;d=39&amp;m=b&amp;r=360p&amp;volume=100&amp;start_res=360p&amp;i=m&amp;options=autostart\" type=\"application\/x-shockwave-flash\" allowscriptaccess=&\nquot;always\" allowfullscreen=\"true\" width=\"648\" height=\"364\"&gt;&lt;\/embed&gt;&lt;\/object&gt;","original_fulltext":""}}