{"content":"13, 20 stycznia 2005 | 1. Projekcja video kultowego filmu Stanleya Kubricka \"2001 Odyseja kosmiczna\", czwartek 13 stycznia, 18.00 ! sala 141 Gm. G\u0142. PW;\n 2. Spotkanie dyskusyjne nt. UFO w perspektywie chrze\u015bcija\u0144skiej, czwartek 20 stycznia, 18.30, sala 141 Gm. G\u0142. PW;\n\n<!--CONTENT FROM OLD SERVER (jos before 2013): 13, 20 stycznia 2005 | 1. Projekcja video kultowego filmu Stanleya Kubricka \"2001 Odyseja kosmiczna\", czwartek 13 stycznia, 18.00 ! sala 141 Gm. G\u0142. PW;\n 2. Spotkanie dyskusyjne nt. UFO w perspektywie chrze\u015bcija\u0144skiej, czwartek 20 stycznia, 18.30, sala 141 Gm. G\u0142. PW;\n-->","source":"jos","title":"UFO na PW!","publish_down":"0000-00-00 00:00:00","created":"2005-01-06 16:09:14","id":"197","original_introtext":"13, 20 stycznia 2005 | 1. Projekcja video kultowego filmu Stanleya Kubricka \"2001 Odyseja kosmiczna\", czwartek 13 stycznia, 18.00 ! sala 141 Gm. G\u0142. PW;<br> 2. Spotkanie dyskusyjne nt. UFO w perspektywie chrze\u015bcija\u0144skiej, czwartek 20 stycznia, 18.30, sala 141 Gm. G\u0142. PW;","original_fulltext":"","text-date":"13, 20 stycznia 2005","after-2013-move":{"content":"13, 20 stycznia 2005 | 1. Projekcja video kultowego filmu Stanleya Kubricka \"2001 Odyseja kosmiczna\", czwartek 13 stycznia, 18.00 ! sala 141 Gm. G\u0142. PW;\n 2. Spotkanie dyskusyjne nt. UFO w perspektywie chrze\u015bcija\u0144skiej, czwartek 20 stycznia, 18.30, sala 141 Gm. G\u0142. PW;","source":"jom","title":"UFO na PW!","publish_down":"0000-00-00 00:00:00","created":"2013-05-08 20:59:32","id":"197","original_introtext":"13, 20 stycznia 2005 | 1. Projekcja video kultowego filmu Stanleya Kubricka \"2001 Odyseja kosmiczna\", czwartek 13 stycznia, 18.00 ! sala 141 Gm. G\u0142. PW;<br> 2. Spotkanie dyskusyjne nt. UFO w perspektywie chrze\u015bcija\u0144skiej, czwartek 20 stycznia, 18.30, sala 141 Gm. G\u0142. PW;","original_fulltext":"","text-date":"13, 20 stycznia 2005"}}